graphiti_core_falkordb/__init__.py
graphiti_core_falkordb/edges.py
graphiti_core_falkordb/errors.py
graphiti_core_falkordb/graph_queries.py
graphiti_core_falkordb/graphiti.py
graphiti_core_falkordb/graphiti_types.py
graphiti_core_falkordb/helpers.py
graphiti_core_falkordb/nodes.py
graphiti_core_falkordb/py.typed
graphiti_core_falkordb/cross_encoder/__init__.py
graphiti_core_falkordb/cross_encoder/bge_reranker_client.py
graphiti_core_falkordb/cross_encoder/client.py
graphiti_core_falkordb/cross_encoder/gemini_reranker_client.py
graphiti_core_falkordb/cross_encoder/openai_reranker_client.py
graphiti_core_falkordb/driver/__init__.py
graphiti_core_falkordb/driver/driver.py
graphiti_core_falkordb/driver/falkordb_driver.py
graphiti_core_falkordb/driver/neo4j_driver.py
graphiti_core_falkordb/embedder/__init__.py
graphiti_core_falkordb/embedder/azure_openai.py
graphiti_core_falkordb/embedder/client.py
graphiti_core_falkordb/embedder/gemini.py
graphiti_core_falkordb/embedder/openai.py
graphiti_core_falkordb/embedder/voyage.py
graphiti_core_falkordb/llm_client/__init__.py
graphiti_core_falkordb/llm_client/anthropic_client.py
graphiti_core_falkordb/llm_client/azure_openai_client.py
graphiti_core_falkordb/llm_client/client.py
graphiti_core_falkordb/llm_client/config.py
graphiti_core_falkordb/llm_client/errors.py
graphiti_core_falkordb/llm_client/gemini_client.py
graphiti_core_falkordb/llm_client/groq_client.py
graphiti_core_falkordb/llm_client/openai_base_client.py
graphiti_core_falkordb/llm_client/openai_client.py
graphiti_core_falkordb/llm_client/openai_generic_client.py
graphiti_core_falkordb/llm_client/utils.py
graphiti_core_falkordb/models/__init__.py
graphiti_core_falkordb/models/edges/__init__.py
graphiti_core_falkordb/models/edges/edge_db_queries.py
graphiti_core_falkordb/models/nodes/__init__.py
graphiti_core_falkordb/models/nodes/node_db_queries.py
graphiti_core_falkordb/prompts/__init__.py
graphiti_core_falkordb/prompts/dedupe_edges.py
graphiti_core_falkordb-0.19.10.dist-info/METADATA
graphiti_core_falkordb-0.19.10.dist-info/WHEEL
graphiti_core_falkordb-0.19.10.dist-info/licenses/LICENSE
graphiti_core_falkordb-0.19.10.dist-info/RECORD
