Metadata-Version: 2.4
Name: graphiti-core-falkordb
Version: 0.19.10
Summary: A temporal graph building library
Project-URL: Homepage, https://help.getzep.com/graphiti/graphiti/overview
Project-URL: Repository, https://github.com/getzep/graphiti
Author-email: Paul Paliychuk <paul@getzep.com>, Preston Rasmussen <preston@getzep.com>, Daniel Chalef <daniel@getzep.com>
License-Expression: Apache-2.0
License-File: LICENSE
Requires-Python: <4,>=3.10
Requires-Dist: diskcache>=5.6.3
Requires-Dist: neo4j>=5.26.0
Requires-Dist: numpy>=1.0.0
Requires-Dist: openai>=1.91.0
Requires-Dist: posthog>=3.0.0
Requires-Dist: pydantic>=2.11.5
Requires-Dist: python-dotenv>=1.0.1
Requires-Dist: tenacity>=9.0.0
Provides-Extra: anthropic
Requires-Dist: anthropic>=0.49.0; extra == 'anthropic'
Provides-Extra: dev
Requires-Dist: anthropic>=0.49.0; extra == 'dev'
Requires-Dist: diskcache-stubs>=5.6.3.6.20240818; extra == 'dev'
Requires-Dist: falkordb<2.0.0,>=1.1.2; extra == 'dev'
Requires-Dist: google-genai>=1.8.0; extra == 'dev'
Requires-Dist: groq>=0.2.0; extra == 'dev'
Requires-Dist: ipykernel>=6.29.5; extra == 'dev'
Requires-Dist: jupyterlab>=4.2.4; extra == 'dev'
Requires-Dist: langchain-anthropic>=0.2.4; extra == 'dev'
Requires-Dist: langchain-openai>=0.2.6; extra == 'dev'
Requires-Dist: langgraph>=0.2.15; extra == 'dev'
Requires-Dist: langsmith>=0.1.108; extra == 'dev'
Requires-Dist: pyright>=1.1.380; extra == 'dev'
Requires-Dist: pytest-asyncio>=0.24.0; extra == 'dev'
Requires-Dist: pytest-xdist>=3.6.1; extra == 'dev'
Requires-Dist: pytest>=8.3.3; extra == 'dev'
Requires-Dist: ruff>=0.7.1; extra == 'dev'
Requires-Dist: sentence-transformers>=3.2.1; extra == 'dev'
Requires-Dist: transformers>=4.45.2; extra == 'dev'
Requires-Dist: voyageai>=0.2.3; extra == 'dev'
Provides-Extra: falkordb
Requires-Dist: falkordb<2.0.0,>=1.1.2; extra == 'falkordb'
Provides-Extra: google-genai
Requires-Dist: google-genai>=1.8.0; extra == 'google-genai'
Provides-Extra: groq
Requires-Dist: groq>=0.2.0; extra == 'groq'
Provides-Extra: sentence-transformers
Requires-Dist: sentence-transformers>=3.2.1; extra == 'sentence-transformers'
Provides-Extra: voyageai
Requires-Dist: voyageai>=0.2.3; extra == 'voyageai'
